seaturtle_menu/__init__.py
seaturtle_menu/bullets.py
seaturtle_menu/consts.py
seaturtle_menu/menu.py
seaturtle_menu/utils.py
seaturtle_menu-1.2.1.dist-info/LICENSE
seaturtle_menu-1.2.1.dist-info/METADATA
seaturtle_menu-1.2.1.dist-info/WHEEL
seaturtle_menu-1.2.1.dist-info/top_level.txt
seaturtle_menu-1.2.1.dist-info/RECORD
