Metadata-Version: 2.1
Name: seaturtle_menu
Version: 1.2.1
Summary: Make effective terminal menus quickly and concisely.
Author: Tathya Garg
Author-email: Tathya Garg <tathya.garg@gmail.com>
Maintainer-email: Tathya Garg <tathya.garg@gmail.com>
License: Copyright 2024 Tathya Garg
Project-URL: Homepage, https://github.com/tathyagarg/seaturtle_menu
Project-URL: Documentation, https://github.com/tathyagarg/seaturtle_menu
Project-URL: Repository, https://github.com/tathyagarg/seaturtle_menu
Project-URL: Changelog, https://github.com/tathyagarg/seaturtle_menu/blob/main/CHANGELOG.md
Keywords: menu
Requires-Python: >=3.12
License-File: LICENSE
